{"_id":"23a1c4da-0290-48f2-9107-482d2597d36b","_ownerId":"00000000-0000-0000-0000-000000000000","answeredAt":"2016-09-27T05:16:24Z","bridgedAt":"2016-09-27T05:16:24Z","callDuration":93000,"calleePhoneNumber":"+77787463340","callerPhoneNumber":"+77073300189","conversationDuration":83000,"createdAt":"2016-09-27T05:16:14Z","createdBy":"00000000-0000-0000-0000-000000000000","direction":1,"directionDisplay":{"icon":"call_received","status":"Входящий вызов"},"displayCallDuration":"01:33","displayConvDuration":"01:23","displayWatingDuration":"00:10","endpointPhoneNumber":"+77012112416","hangupedAt":"2016-09-27T05:17:47Z","initChannel":"sofia/external/+77073300189@172.16.240.20:5060","recordFile":"/hooks/calls/record/23a1c4da-0290-48f2-9107-482d2597d36b","startedAt":"2016-09-27T05:16:14Z","status":3,"statusDisplay":{"color":"#4CAF50","icon":"done","status":"Успешный звонок"},"updatedAt":"2016-09-27T05:17:47Z","updatedBy":"00000000-0000-0000-0000-000000000000","watingDuration":10000}