{"_id":"6b923782-3ad8-493d-85f8-bd322ced46a8","_ownerId":"00000000-0000-0000-0000-000000000000","answeredAt":"2016-09-28T08:21:14Z","bridgedAt":"2016-09-28T08:21:14Z","callDuration":159000,"calleePhoneNumber":"87273250700","callerPhoneNumber":"87019320228","conversationDuration":149000,"createdAt":"2016-09-28T08:21:04Z","createdBy":"00000000-0000-0000-0000-000000000000","direction":1,"directionDisplay":{"icon":"call_received","status":"Входящий вызов"},"displayCallDuration":"02:39","displayConvDuration":"02:29","displayWatingDuration":"00:10","endpointPhoneNumber":"87775550504","hangupedAt":"2016-09-28T08:23:43Z","initChannel":"sofia/external/87019320228@31.171.162.20","recordFile":"/hooks/calls/record/6b923782-3ad8-493d-85f8-bd322ced46a8","startedAt":"2016-09-28T08:21:04Z","status":3,"statusDisplay":{"color":"#4CAF50","icon":"done","status":"Успешный звонок"},"updatedAt":"2016-09-28T08:23:43Z","updatedBy":"00000000-0000-0000-0000-000000000000","watingDuration":10000}