{"_id":"6fdae5d6-1c5f-4799-82b0-9ef317e7faed","_ownerId":"00000000-0000-0000-0000-000000000000","answeredAt":"2016-10-13T03:31:41Z","bridgedAt":"2016-10-13T03:31:42Z","callDuration":79000,"calleePhoneNumber":"87273250600","callerPhoneNumber":"87089711180","conversationDuration":70000,"createdAt":"2016-10-13T03:31:32Z","createdBy":"00000000-0000-0000-0000-000000000000","direction":1,"directionDisplay":{"icon":"call_received","status":"Входящий вызов"},"displayCallDuration":"01:19","displayConvDuration":"01:10","displayWatingDuration":"00:09","endpointPhoneNumber":"+77089717149","hangupedAt":"2016-10-13T03:32:51Z","initChannel":"sofia/external/87089711180@31.171.162.20","recordFile":"/hooks/calls/record/6fdae5d6-1c5f-4799-82b0-9ef317e7faed","startedAt":"2016-10-13T03:31:32Z","status":3,"statusDisplay":{"color":"#4CAF50","icon":"done","status":"Успешный звонок"},"updatedAt":"2016-10-13T03:32:51Z","updatedBy":"00000000-0000-0000-0000-000000000000","watingDuration":9000}