{"_id":"4c84eb83-5f3f-4665-a4e7-263144807487","_ownerId":"00000000-0000-0000-0000-000000000000","callDuration":0,"calleePhoneNumber":"909141","callerPhoneNumber":"7755513697","createdAt":"2016-10-27T06:13:00Z","createdBy":"00000000-0000-0000-0000-000000000000","direction":1,"directionDisplay":{"icon":"call_received","status":"Входящий вызов"},"displayCallDuration":"--:--","displayConvDuration":"--:--","displayWatingDuration":"--:--","hangupedAt":"2016-10-27T06:13:00Z","initChannel":"sofia/external/7755513697@79.140.224.215","startedAt":"2016-10-27T06:13:00Z","status":4,"statusDisplay":{"color":"","icon":"call_missed","status":"Никто не ответил"},"updatedAt":"2016-10-27T06:13:00Z","updatedBy":"00000000-0000-0000-0000-000000000000","watingDuration":0}