{"_id":"77bcb34f-8bda-4e7f-9db0-bf7b4efcf9fe","_ownerId":"00000000-0000-0000-0000-000000000000","callDuration":0,"calleePhoneNumber":"909141","callerPhoneNumber":"908938","createdAt":"2016-10-27T08:58:01Z","createdBy":"00000000-0000-0000-0000-000000000000","direction":1,"directionDisplay":{"icon":"call_received","status":"Входящий вызов"},"displayCallDuration":"--:--","displayConvDuration":"--:--","displayWatingDuration":"--:--","hangupedAt":"2016-10-27T08:58:01Z","initChannel":"sofia/external/908938@79.140.224.215","startedAt":"2016-10-27T08:58:01Z","status":4,"statusDisplay":{"color":"","icon":"call_missed","status":"Никто не ответил"},"updatedAt":"2016-10-27T08:58:01Z","updatedBy":"00000000-0000-0000-0000-000000000000","watingDuration":0}