{"_id":"f1f83985-6814-45c4-a619-f43118d233f7","callerPhoneNumber":"255585","calleePhoneNumber":"912515","startedAt":"2016-11-17T08:39:42.733Z","status":3,"direction":1,"initChannel":"sofia/external/255585@79.140.224.215","createdAt":"2016-11-17T08:39:42.785Z","createdBy":"system","_ownerId":"system","__v":4,"answeredAt":"2016-11-17T08:40:00.203Z","endpointPhoneNumber":"909001","recordFile":"/hooks/calls/record/f1f83985-6814-45c4-a619-f43118d233f7","watingDuration":17470,"updatedAt":"2016-11-17T08:47:06.034Z","updatedBy":"system","bridgedAt":"2016-11-17T08:40:00.204Z","hangupedAt":"2016-11-17T08:47:05.994Z","conversationDuration":425791,"callDuration":443261,"directionDisplay":{"icon":"call_received","status":"Входящий вызов"},"displayCallDuration":"07:23","displayConvDuration":"07:06","displayWatingDuration":"00:17","statusDisplay":{"icon":"done","status":"Успешный звонок","color":"#4CAF50"}}