{"_id":"448a377b-9d15-4f95-affc-4ef1a52b3419","callerPhoneNumber":"+77783687827","calleePhoneNumber":"+77787463348","startedAt":"2016-11-17T08:16:11.155Z","status":3,"direction":1,"initChannel":"sofia/external/+77783687827@172.16.240.20:5060","createdAt":"2016-11-17T08:16:11.209Z","createdBy":"system","_ownerId":"system","__v":4,"answeredAt":"2016-11-17T08:16:20.231Z","endpointPhoneNumber":"+77079452857","recordFile":"/hooks/calls/record/448a377b-9d15-4f95-affc-4ef1a52b3419","watingDuration":9076,"updatedAt":"2016-11-17T08:16:53.930Z","updatedBy":"system","bridgedAt":"2016-11-17T08:16:20.233Z","hangupedAt":"2016-11-17T08:16:53.917Z","conversationDuration":33686,"callDuration":42762,"directionDisplay":{"icon":"call_received","status":"Входящий вызов"},"displayCallDuration":"00:43","displayConvDuration":"00:34","displayWatingDuration":"00:09","statusDisplay":{"icon":"done","status":"Успешный звонок","color":"#4CAF50"}}