{"_id":"26934304-e04a-4590-a59d-914ef2ffa8bc","callerPhoneNumber":"+77081170379","calleePhoneNumber":"+77787463343","startedAt":"2016-12-02T11:08:25.578Z","status":4,"direction":1,"initChannel":"sofia/external/+77081170379@172.16.240.20:5060","createdAt":"2016-12-02T11:08:25.597Z","createdBy":"system","_ownerId":"system","__v":2,"hangupedAt":"2016-12-02T11:08:25.950Z","watingDuration":372,"callDuration":372,"updatedAt":"2016-12-02T11:08:25.954Z","updatedBy":"system","directionDisplay":{"icon":"call_received","status":"Входящий вызов"},"displayCallDuration":"00:00","displayConvDuration":"--:--","displayWatingDuration":"00:00","statusDisplay":{"icon":"call_missed","status":"Никто не ответил","color":""}}