{"_id":"8f150f6e-c57b-4a81-986e-dfd20a19afbd","callerPhoneNumber":"87172301430","calleePhoneNumber":"87172772717","startedAt":"2016-12-07T04:01:41.598Z","status":3,"direction":1,"initChannel":"sofia/external/87172301430@31.171.162.20","createdAt":"2016-12-07T04:01:41.621Z","createdBy":"system","_ownerId":"system","__v":4,"answeredAt":"2016-12-07T04:01:56.936Z","endpointPhoneNumber":"87052921353","recordFile":"/hooks/calls/record/8f150f6e-c57b-4a81-986e-dfd20a19afbd","watingDuration":15338,"updatedAt":"2016-12-07T04:02:22.970Z","updatedBy":"system","bridgedAt":"2016-12-07T04:01:56.937Z","hangupedAt":"2016-12-07T04:02:22.963Z","conversationDuration":26027,"callDuration":41365,"directionDisplay":{"icon":"call_received","status":"Входящий вызов"},"displayCallDuration":"00:41","displayConvDuration":"00:26","displayWatingDuration":"00:15","statusDisplay":{"icon":"done","status":"Успешный звонок","color":"#4CAF50"}}