{"_id":"a980f0dd-803c-47d1-9edf-34dde8d6317a","callerPhoneNumber":"+77013352372","calleePhoneNumber":"+77787463348","startedAt":"2016-12-21T04:23:31.020Z","status":3,"direction":1,"initChannel":"sofia/external/+77013352372@172.16.240.20:5060","createdAt":"2016-12-21T04:23:31.064Z","createdBy":"system","_ownerId":"system","__v":4,"bridgedAt":"2016-12-21T04:23:38.763Z","updatedAt":"2016-12-21T04:24:26.514Z","updatedBy":"system","answeredAt":"2016-12-21T04:23:38.760Z","endpointPhoneNumber":"+77079452857","recordFile":"/hooks/calls/record/a980f0dd-803c-47d1-9edf-34dde8d6317a","watingDuration":7740,"hangupedAt":"2016-12-21T04:24:26.501Z","conversationDuration":47741,"callDuration":55481,"directionDisplay":{"icon":"call_received","status":"Входящий вызов"},"displayCallDuration":"00:55","displayConvDuration":"00:48","displayWatingDuration":"00:08","statusDisplay":{"icon":"done","status":"Успешный звонок","color":"#4CAF50"}}