{"_id":"b93e99d9-8435-4656-82b0-0de33f536529","callerPhoneNumber":"+77015885355","calleePhoneNumber":"+77787463342","startedAt":"2016-12-20T05:42:58.221Z","status":3,"direction":1,"initChannel":"sofia/external/+77015885355@172.16.240.20:5060","createdAt":"2016-12-20T05:42:58.249Z","createdBy":"system","_ownerId":"system","__v":4,"bridgedAt":"2016-12-20T05:43:10.302Z","updatedAt":"2016-12-20T05:43:51.462Z","updatedBy":"system","answeredAt":"2016-12-20T05:43:10.301Z","endpointPhoneNumber":"+77079452857","recordFile":"/hooks/calls/record/b93e99d9-8435-4656-82b0-0de33f536529","watingDuration":12080,"hangupedAt":"2016-12-20T05:43:51.442Z","conversationDuration":41141,"callDuration":53221,"directionDisplay":{"icon":"call_received","status":"Входящий вызов"},"displayCallDuration":"00:53","displayConvDuration":"00:41","displayWatingDuration":"00:12","statusDisplay":{"icon":"done","status":"Успешный звонок","color":"#4CAF50"}}