{"_id":"b7dd7c60-1279-4982-b13e-85ec717d52ee","callerPhoneNumber":"+77019320228","calleePhoneNumber":"+77780218789","startedAt":"2016-12-21T16:29:52.765Z","status":3,"direction":1,"initChannel":"sofia/external/+77019320228@172.16.240.20:5060","createdAt":"2016-12-21T16:29:52.783Z","createdBy":"system","_ownerId":"system","__v":4,"bridgedAt":"2016-12-21T16:30:00.115Z","updatedAt":"2016-12-21T16:30:24.056Z","updatedBy":"system","answeredAt":"2016-12-21T16:30:00.114Z","endpointPhoneNumber":"+77765544888","recordFile":"/hooks/calls/record/b7dd7c60-1279-4982-b13e-85ec717d52ee","watingDuration":7349,"hangupedAt":"2016-12-21T16:30:24.051Z","conversationDuration":23937,"callDuration":31286,"directionDisplay":{"icon":"call_received","status":"Входящий вызов"},"displayCallDuration":"00:31","displayConvDuration":"00:24","displayWatingDuration":"00:07","statusDisplay":{"icon":"done","status":"Успешный звонок","color":"#4CAF50"}}