{"_id":"6416fc34-4b14-4ab0-bac7-886ecf43fad0","callerPhoneNumber":"+77752609898","calleePhoneNumber":"+77787463340","startedAt":"2016-12-28T10:33:07.218Z","status":3,"direction":1,"initChannel":"sofia/external/+77752609898@172.16.240.20:5060","createdAt":"2016-12-28T10:33:07.239Z","createdBy":"system","_ownerId":"system","__v":4,"answeredAt":"2016-12-28T10:33:18.659Z","endpointPhoneNumber":"+77785301421","recordFile":"/hooks/calls/record/6416fc34-4b14-4ab0-bac7-886ecf43fad0","watingDuration":11441,"updatedAt":"2016-12-28T10:34:23.168Z","updatedBy":"system","bridgedAt":"2016-12-28T10:33:18.665Z","hangupedAt":"2016-12-28T10:34:23.129Z","conversationDuration":64470,"callDuration":75911,"directionDisplay":{"icon":"call_received","status":"Входящий вызов"},"displayCallDuration":"01:16","displayConvDuration":"01:04","displayWatingDuration":"00:11","statusDisplay":{"icon":"done","status":"Успешный звонок","color":"#4CAF50"}}