{"_id":"e30b3c4b-7205-4dfc-bd38-d0a1d797015c","callerPhoneNumber":"+77473983773","calleePhoneNumber":"+77787463348","startedAt":"2016-12-23T02:54:10.153Z","status":4,"direction":1,"initChannel":"sofia/external/+77473983773@172.16.240.20:5060","createdAt":"2016-12-23T02:54:10.343Z","createdBy":"system","_ownerId":"system","__v":2,"hangupedAt":"2016-12-23T02:54:19.179Z","watingDuration":9026,"callDuration":9026,"updatedAt":"2016-12-23T02:54:19.200Z","updatedBy":"system","directionDisplay":{"icon":"call_received","status":"Входящий вызов"},"displayCallDuration":"00:09","displayConvDuration":"--:--","displayWatingDuration":"00:09","statusDisplay":{"icon":"call_missed","status":"Никто не ответил","color":""}}