{"_id":"71098659-27a9-4d3a-90b8-81a91a692b66","callerPhoneNumber":"+77756159196","calleePhoneNumber":"+77787463348","startedAt":"2017-01-05T13:02:53.636Z","status":4,"direction":1,"initChannel":"sofia/external/+77756159196@172.16.240.20:5060","createdAt":"2017-01-05T13:02:53.664Z","createdBy":"system","_ownerId":"system","__v":2,"hangupedAt":"2017-01-05T13:03:22.716Z","watingDuration":29080,"callDuration":29080,"updatedAt":"2017-01-05T13:03:22.735Z","updatedBy":"system","directionDisplay":{"icon":"call_received","status":"Входящий вызов"},"displayCallDuration":"00:29","displayConvDuration":"--:--","displayWatingDuration":"00:29","statusDisplay":{"icon":"call_missed","status":"Никто не ответил","color":""}}