{"_id":"4a4384e8-972e-4e8a-b246-4ab396708eb4","callerPhoneNumber":"7273509952","calleePhoneNumber":"910060","startedAt":"2017-01-09T07:34:22.800Z","status":3,"direction":1,"initChannel":"sofia/external/7273509952@79.140.224.215","createdAt":"2017-01-09T07:34:22.815Z","createdBy":"system","_ownerId":"system","__v":4,"answeredAt":"2017-01-09T07:34:37.679Z","endpointPhoneNumber":"909001","recordFile":"/hooks/calls/record/4a4384e8-972e-4e8a-b246-4ab396708eb4","watingDuration":14879,"updatedAt":"2017-01-09T07:34:38.805Z","updatedBy":"system","bridgedAt":"2017-01-09T07:34:37.680Z","hangupedAt":"2017-01-09T07:34:38.783Z","conversationDuration":1104,"callDuration":15983,"directionDisplay":{"icon":"call_received","status":"Входящий вызов"},"displayCallDuration":"00:16","displayConvDuration":"00:01","displayWatingDuration":"00:15","statusDisplay":{"icon":"done","status":"Успешный звонок","color":"#4CAF50"}}