{"_id":"40302752-14f4-4307-8c0d-b00938d3fb84","callerPhoneNumber":"+77477289369","calleePhoneNumber":"+77780218740","startedAt":"2017-01-20T07:14:27.037Z","status":3,"direction":1,"initChannel":"sofia/external/+77477289369@172.16.240.20:5060","createdAt":"2017-01-20T07:14:27.058Z","createdBy":"system","_ownerId":"system","__v":4,"answeredAt":"2017-01-20T07:14:35.423Z","endpointPhoneNumber":"+77012117087","recordFile":"/hooks/calls/record/40302752-14f4-4307-8c0d-b00938d3fb84","watingDuration":8386,"updatedAt":"2017-01-20T07:15:11.033Z","updatedBy":"system","bridgedAt":"2017-01-20T07:14:35.425Z","hangupedAt":"2017-01-20T07:15:11.019Z","conversationDuration":35596,"callDuration":43982,"directionDisplay":{"icon":"call_received","status":"Входящий вызов"},"displayCallDuration":"00:44","displayConvDuration":"00:36","displayWatingDuration":"00:08","statusDisplay":{"icon":"done","status":"Успешный звонок","color":"#4CAF50"}}