{"_id":"77d61683-16d4-4ce9-bf68-9960fb30cd4c","callerPhoneNumber":"+77022999311","calleePhoneNumber":"+77787463343","startedAt":"2017-01-13T11:07:14.655Z","status":3,"direction":1,"initChannel":"sofia/external/+77022999311@172.16.240.20:5060","createdAt":"2017-01-13T11:07:14.671Z","createdBy":"system","_ownerId":"system","__v":4,"answeredAt":"2017-01-13T11:07:22.976Z","endpointPhoneNumber":"+77783449417","recordFile":"/hooks/calls/record/77d61683-16d4-4ce9-bf68-9960fb30cd4c","watingDuration":8321,"updatedAt":"2017-01-13T11:07:56.165Z","updatedBy":"system","bridgedAt":"2017-01-13T11:07:22.986Z","hangupedAt":"2017-01-13T11:07:56.159Z","conversationDuration":33183,"callDuration":41504,"directionDisplay":{"icon":"call_received","status":"Входящий вызов"},"displayCallDuration":"00:42","displayConvDuration":"00:33","displayWatingDuration":"00:08","statusDisplay":{"icon":"done","status":"Успешный звонок","color":"#4CAF50"}}