{"_id":"d7611f64-8965-45b7-b4d9-e33738a003e5","callerPhoneNumber":"+77013822622","calleePhoneNumber":"+77787463343","startedAt":"2017-01-11T14:39:48.370Z","status":4,"direction":1,"initChannel":"sofia/external/+77013822622@172.16.240.20:5060","createdAt":"2017-01-11T14:39:48.390Z","createdBy":"system","_ownerId":"system","__v":2,"hangupedAt":"2017-01-11T14:40:04.887Z","watingDuration":16517,"callDuration":16517,"updatedAt":"2017-01-11T14:40:04.909Z","updatedBy":"system","directionDisplay":{"icon":"call_received","status":"Входящий вызов"},"displayCallDuration":"00:17","displayConvDuration":"--:--","displayWatingDuration":"00:17","statusDisplay":{"icon":"call_missed","status":"Никто не ответил","color":""}}