{"_id":"81540399-9933-4f59-bab9-6c70ab35a128","callerPhoneNumber":"7024262644","calleePhoneNumber":"912515","startedAt":"2017-01-14T05:57:46.912Z","status":3,"direction":1,"initChannel":"sofia/external/7024262644@79.140.224.215","createdAt":"2017-01-14T05:57:46.934Z","createdBy":"system","_ownerId":"system","__v":4,"bridgedAt":"2017-01-14T05:57:57.762Z","updatedAt":"2017-01-14T05:58:21.188Z","updatedBy":"system","answeredAt":"2017-01-14T05:57:57.761Z","endpointPhoneNumber":"909001","recordFile":"/hooks/calls/record/81540399-9933-4f59-bab9-6c70ab35a128","watingDuration":10849,"hangupedAt":"2017-01-14T05:58:21.166Z","conversationDuration":23405,"callDuration":34254,"directionDisplay":{"icon":"call_received","status":"Входящий вызов"},"displayCallDuration":"00:34","displayConvDuration":"00:23","displayWatingDuration":"00:11","statusDisplay":{"icon":"done","status":"Успешный звонок","color":"#4CAF50"}}