{"_id":"52ba30c7-4d58-4d8a-8798-5dc33cfb4d64","callerPhoneNumber":"+77019320228","calleePhoneNumber":"+77470940814","startedAt":"2017-02-02T04:38:16.637Z","status":3,"direction":1,"initChannel":"sofia/external/+77019320228@212.96.83.118","createdAt":"2017-02-02T04:38:16.662Z","createdBy":"system","_ownerId":"system","__v":4,"bridgedAt":"2017-02-02T04:38:25.522Z","updatedAt":"2017-02-02T04:38:49.392Z","updatedBy":"system","answeredAt":"2017-02-02T04:38:25.520Z","endpointPhoneNumber":"+77077670404","recordFile":"/hooks/calls/record/52ba30c7-4d58-4d8a-8798-5dc33cfb4d64","watingDuration":8883,"hangupedAt":"2017-02-02T04:38:49.388Z","conversationDuration":23868,"callDuration":32751,"directionDisplay":{"icon":"call_received","status":"Входящий вызов"},"displayCallDuration":"00:33","displayConvDuration":"00:24","displayWatingDuration":"00:09","statusDisplay":{"icon":"done","status":"Успешный звонок","color":"#4CAF50"}}