{"_id":"cdaf41b8-fd6a-4468-b015-71b3557b3000","callerPhoneNumber":"87273959032","calleePhoneNumber":"87273250700","startedAt":"2017-01-30T06:26:55.993Z","status":3,"direction":1,"initChannel":"sofia/external/87273959032@31.171.162.20","createdAt":"2017-01-30T06:26:56.025Z","createdBy":"system","_ownerId":"system","__v":4,"answeredAt":"2017-01-30T06:27:08.108Z","endpointPhoneNumber":"+77089717150","recordFile":"/hooks/calls/record/cdaf41b8-fd6a-4468-b015-71b3557b3000","watingDuration":12115,"updatedAt":"2017-01-30T06:33:59.420Z","updatedBy":"system","bridgedAt":"2017-01-30T06:27:08.112Z","hangupedAt":"2017-01-30T06:33:59.408Z","conversationDuration":411300,"callDuration":423415,"directionDisplay":{"icon":"call_received","status":"Входящий вызов"},"displayCallDuration":"07:03","displayConvDuration":"06:51","displayWatingDuration":"00:12","statusDisplay":{"icon":"done","status":"Успешный звонок","color":"#4CAF50"}}