{"_id":"d4957a51-4402-4738-b791-1e2efdd7760c","callerPhoneNumber":"+77477228989","calleePhoneNumber":"+77787463343","startedAt":"2017-02-08T11:01:13.037Z","status":3,"direction":1,"initChannel":"sofia/external/+77477228989@172.16.240.20:5060","createdAt":"2017-02-08T11:01:13.060Z","createdBy":"system","_ownerId":"system","__v":4,"answeredAt":"2017-02-08T11:01:21.227Z","endpointPhoneNumber":"+77783449417","recordFile":"/hooks/calls/record/d4957a51-4402-4738-b791-1e2efdd7760c","watingDuration":8190,"updatedAt":"2017-02-08T11:01:38.257Z","updatedBy":"system","bridgedAt":"2017-02-08T11:01:21.230Z","hangupedAt":"2017-02-08T11:01:38.242Z","conversationDuration":17015,"callDuration":25205,"directionDisplay":{"icon":"call_received","status":"Входящий вызов"},"displayCallDuration":"00:25","displayConvDuration":"00:17","displayWatingDuration":"00:08","statusDisplay":{"icon":"done","status":"Успешный звонок","color":"#4CAF50"}}