{"_id":"03988014-25d1-46f8-8c9c-1d6821f48645","callerPhoneNumber":"+77021649192","calleePhoneNumber":"+77787460214","startedAt":"2017-02-07T09:09:33.633Z","status":3,"direction":1,"initChannel":"sofia/external/+77021649192@172.16.240.20:5060","createdAt":"2017-02-07T09:09:33.679Z","createdBy":"system","_ownerId":"system","__v":4,"bridgedAt":"2017-02-07T09:09:40.040Z","updatedAt":"2017-02-07T09:12:07.941Z","updatedBy":"system","answeredAt":"2017-02-07T09:09:40.039Z","endpointPhoneNumber":"+77010999898","recordFile":"/hooks/calls/record/03988014-25d1-46f8-8c9c-1d6821f48645","watingDuration":6406,"hangupedAt":"2017-02-07T09:12:07.935Z","conversationDuration":147896,"callDuration":154302,"directionDisplay":{"icon":"call_received","status":"Входящий вызов"},"displayCallDuration":"02:34","displayConvDuration":"02:28","displayWatingDuration":"00:06","statusDisplay":{"icon":"done","status":"Успешный звонок","color":"#4CAF50"}}