{"_id":"60272f19-442b-469b-bdf1-cc1604545554","callerPhoneNumber":"+77059851187","calleePhoneNumber":"+77787460212","startedAt":"2017-02-03T11:27:14.831Z","status":4,"direction":1,"initChannel":"sofia/external/+77059851187@172.16.240.20:5060","createdAt":"2017-02-03T11:27:14.886Z","createdBy":"system","_ownerId":"system","__v":2,"hangupedAt":"2017-02-03T11:27:36.403Z","watingDuration":21572,"callDuration":21572,"updatedAt":"2017-02-03T11:27:36.432Z","updatedBy":"system","directionDisplay":{"icon":"call_received","status":"Входящий вызов"},"displayCallDuration":"00:22","displayConvDuration":"--:--","displayWatingDuration":"00:22","statusDisplay":{"icon":"call_missed","status":"Никто не ответил","color":""}}