{"_id":"1fc611be-c1c2-49ca-a772-4fc338126bca","callerPhoneNumber":"+77081118788","calleePhoneNumber":"+77787463343","startedAt":"2017-02-03T09:18:08.585Z","status":4,"direction":1,"initChannel":"sofia/external/+77081118788@172.16.240.20:5060","createdAt":"2017-02-03T09:18:08.610Z","createdBy":"system","_ownerId":"system","__v":2,"hangupedAt":"2017-02-03T09:18:11.421Z","watingDuration":2836,"callDuration":2836,"updatedAt":"2017-02-03T09:18:11.433Z","updatedBy":"system","directionDisplay":{"icon":"call_received","status":"Входящий вызов"},"displayCallDuration":"00:03","displayConvDuration":"--:--","displayWatingDuration":"00:03","statusDisplay":{"icon":"call_missed","status":"Никто не ответил","color":""}}