{"_id":"1fdd284a-f7be-4ef9-b204-627bdc876d9b","callerPhoneNumber":"+77777280175","calleePhoneNumber":"+77470941264","startedAt":"2017-02-19T10:08:59.846Z","status":4,"direction":1,"initChannel":"sofia/external/+77777280175@212.96.83.118","createdAt":"2017-02-19T10:08:59.865Z","createdBy":"system","_ownerId":"system","__v":2,"hangupedAt":"2017-02-19T10:09:33.878Z","watingDuration":34032,"callDuration":34032,"updatedAt":"2017-02-19T10:09:33.895Z","updatedBy":"system","directionDisplay":{"icon":"call_received","status":"Входящий вызов"},"displayCallDuration":"00:34","displayConvDuration":"--:--","displayWatingDuration":"00:34","statusDisplay":{"icon":"call_missed","status":"Никто не ответил","color":""}}