{"_id":"ef0cba02-4021-442e-953a-0aff34f0ecc8","callerPhoneNumber":"+77012978956","calleePhoneNumber":"+77787463348","startedAt":"2017-02-19T06:03:19.126Z","status":4,"direction":1,"initChannel":"sofia/external/+77012978956@172.16.240.20:5060","createdAt":"2017-02-19T06:03:19.143Z","createdBy":"system","_ownerId":"system","__v":2,"hangupedAt":"2017-02-19T06:03:59.596Z","watingDuration":40470,"callDuration":40470,"updatedAt":"2017-02-19T06:03:59.619Z","updatedBy":"system","directionDisplay":{"icon":"call_received","status":"Входящий вызов"},"displayCallDuration":"00:40","displayConvDuration":"--:--","displayWatingDuration":"00:40","statusDisplay":{"icon":"call_missed","status":"Никто не ответил","color":""}}