{"_id":"a4b6c891-cd3a-4a49-aba0-b99bf430eeed","callerPhoneNumber":"+77011200282","calleePhoneNumber":"+77787463348","startedAt":"2017-03-14T09:42:32.216Z","status":3,"direction":1,"initChannel":"sofia/external/+77011200282@172.16.240.20:5060","createdAt":"2017-03-14T09:42:32.247Z","createdBy":"system","_ownerId":"system","__v":4,"bridgedAt":"2017-03-14T09:42:43.482Z","updatedAt":"2017-03-14T09:48:06.497Z","updatedBy":"system","answeredAt":"2017-03-14T09:42:43.475Z","endpointPhoneNumber":"+77079452857","recordFile":"/hooks/calls/record/a4b6c891-cd3a-4a49-aba0-b99bf430eeed","watingDuration":11259,"hangupedAt":"2017-03-14T09:48:06.482Z","conversationDuration":323007,"callDuration":334266,"directionDisplay":{"icon":"call_received","status":"Входящий вызов"},"displayCallDuration":"05:34","displayConvDuration":"05:23","displayWatingDuration":"00:11","statusDisplay":{"icon":"done","status":"Успешный звонок","color":"#4CAF50"}}