{"_id":"9cf38008-9ed3-47e8-a4d7-93862915b3e8","callerPhoneNumber":"+77079558335","calleePhoneNumber":"+77787463343","startedAt":"2017-03-10T09:58:08.256Z","status":3,"direction":1,"initChannel":"sofia/external/+77079558335@172.16.240.20:5060","createdAt":"2017-03-10T09:58:08.275Z","createdBy":"system","_ownerId":"system","__v":4,"answeredAt":"2017-03-10T09:58:15.506Z","endpointPhoneNumber":"+77783449417","recordFile":"/hooks/calls/record/9cf38008-9ed3-47e8-a4d7-93862915b3e8","watingDuration":7250,"updatedAt":"2017-03-10T10:00:06.217Z","updatedBy":"system","bridgedAt":"2017-03-10T09:58:15.508Z","hangupedAt":"2017-03-10T10:00:06.213Z","conversationDuration":110707,"callDuration":117957,"directionDisplay":{"icon":"call_received","status":"Входящий вызов"},"displayCallDuration":"01:58","displayConvDuration":"01:51","displayWatingDuration":"00:07","statusDisplay":{"icon":"done","status":"Успешный звонок","color":"#4CAF50"}}