{"_id":"872a5a5d-d210-44b6-ac45-e6b05da8ee92","callerPhoneNumber":"+77776582475","calleePhoneNumber":"+77787460214","startedAt":"2017-03-08T03:30:56.163Z","status":3,"direction":1,"initChannel":"sofia/external/+77776582475@172.16.240.20:5060","createdAt":"2017-03-08T03:30:56.199Z","createdBy":"system","_ownerId":"system","__v":4,"bridgedAt":"2017-03-08T03:31:15.442Z","updatedAt":"2017-03-08T03:31:31.076Z","updatedBy":"system","answeredAt":"2017-03-08T03:31:15.442Z","endpointPhoneNumber":"+77010999898","recordFile":"/hooks/calls/record/872a5a5d-d210-44b6-ac45-e6b05da8ee92","watingDuration":19279,"hangupedAt":"2017-03-08T03:31:31.061Z","conversationDuration":15619,"callDuration":34898,"directionDisplay":{"icon":"call_received","status":"Входящий вызов"},"displayCallDuration":"00:35","displayConvDuration":"00:16","displayWatingDuration":"00:19","statusDisplay":{"icon":"done","status":"Успешный звонок","color":"#4CAF50"}}