{"_id":"250a4c16-d4fd-4f81-92c0-1ec6f562c835","callerPhoneNumber":"87273722292","calleePhoneNumber":"87273250700","startedAt":"2017-03-14T06:48:49.806Z","status":3,"direction":1,"initChannel":"sofia/external/87273722292@31.171.162.20","createdAt":"2017-03-14T06:48:49.837Z","createdBy":"system","_ownerId":"system","__v":4,"answeredAt":"2017-03-14T06:49:07.956Z","endpointPhoneNumber":"87089717149","recordFile":"/hooks/calls/record/250a4c16-d4fd-4f81-92c0-1ec6f562c835","watingDuration":18150,"updatedAt":"2017-03-14T06:49:14.223Z","updatedBy":"system","bridgedAt":"2017-03-14T06:49:07.962Z","hangupedAt":"2017-03-14T06:49:14.206Z","conversationDuration":6250,"callDuration":24400,"directionDisplay":{"icon":"call_received","status":"Входящий вызов"},"displayCallDuration":"00:24","displayConvDuration":"00:06","displayWatingDuration":"00:18","statusDisplay":{"icon":"done","status":"Успешный звонок","color":"#4CAF50"}}