{"_id":"a70cc98f-133e-4345-83b4-095bdd7eeea5","callerPhoneNumber":"908942","calleePhoneNumber":"909066","startedAt":"2017-02-22T10:05:40.481Z","status":4,"direction":1,"initChannel":"sofia/external/908942@79.140.224.215","createdAt":"2017-02-22T10:05:40.517Z","createdBy":"system","_ownerId":"system","__v":2,"hangupedAt":"2017-02-22T10:05:40.580Z","watingDuration":99,"callDuration":99,"updatedAt":"2017-02-22T10:05:40.585Z","updatedBy":"system","directionDisplay":{"icon":"call_received","status":"Входящий вызов"},"displayCallDuration":"00:00","displayConvDuration":"--:--","displayWatingDuration":"00:00","statusDisplay":{"icon":"call_missed","status":"Никто не ответил","color":""}}