{"_id":"e205ba7b-0b6f-42a5-bb4f-7d4af619d0fe","callerPhoneNumber":"+77471541899","calleePhoneNumber":"+77780218788","startedAt":"2017-05-22T04:37:38.987Z","status":0,"direction":1,"initChannel":"sofia/external/+77471541899@172.16.240.20:5060","createdAt":"2017-05-22T04:37:39.148Z","createdBy":"system","_ownerId":"system","__v":1,"directionDisplay":{"icon":"call_received","status":"Входящий вызов"},"displayCallDuration":"--:--","displayConvDuration":"--:--","displayWatingDuration":"--:--","statusDisplay":{"icon":"ring_volume","status":"Звонок поступил на АТС","color":""}}