{"answeredAt":"","bridgedAt":"2017-06-11T11:14:01","callDuration":171000,"calleePhoneNumber":"87470941202","callerPhoneNumber":"87765544888","conversationDuration":163000,"createdAt":"2017-06-11T11:14:01","direction":"1","displayCallDuration":"00:30","displayConvDuration":"00:00","displayWatingDuration":"00:30","endpointPhoneNumber":"87718996450","hangupedAt":"2017-06-11T11:14:31","startedAt":"2017-06-11T11:14:01","recordFile":"","status":4,"watingDuration":30000,"asterisk_call_id":1497179641,"crm_call_id":""}