{"answeredAt":"2017-06-01T08:06:09","bridgedAt":"2017-06-01T08:06:00","callDuration":171000,"calleePhoneNumber":"87787463348","callerPhoneNumber":"87781611539","conversationDuration":163000,"createdAt":"2017-06-01T08:06:00","direction":"1","displayCallDuration":"01:40","displayConvDuration":"01:31","displayWatingDuration":"00:09","endpointPhoneNumber":"87079452857","hangupedAt":"2017-06-01T08:07:41","startedAt":"2017-06-01T08:06:00","recordFile":"http://185.22.65.50/monitor/2017/06/01/in-+77787463348-+77781611539-20170601-140600-1496304360.4056.wav","status":3,"watingDuration":9000,"asterisk_call_id":1496304360,"crm_call_id":""}