{"answeredAt":"2017-06-02T08:22:12","bridgedAt":"2017-06-02T08:21:59","callDuration":171000,"calleePhoneNumber":"87787460214","callerPhoneNumber":"87015333923","conversationDuration":163000,"createdAt":"2017-06-02T08:21:59","direction":"1","displayCallDuration":"00:26","displayConvDuration":"00:13","displayWatingDuration":"00:13","endpointPhoneNumber":"87010999898","hangupedAt":"2017-06-02T08:22:25","startedAt":"2017-06-02T08:21:59","recordFile":"http://185.22.65.50/monitor/2017/06/02/in-+77787460214-+77015333923-20170602-142159-1496391719.4429.wav","status":3,"watingDuration":13000,"asterisk_call_id":1496391719,"crm_call_id":""}