{"answeredAt":"2017-06-19T06:17:06","bridgedAt":"2017-06-19T06:16:55","callDuration":171000,"calleePhoneNumber":"87470941200","callerPhoneNumber":"87017818681","conversationDuration":163000,"createdAt":"2017-06-19T06:16:55","direction":"1","displayCallDuration":"00:45","displayConvDuration":"00:34","displayWatingDuration":"00:11","endpointPhoneNumber":"87212909001","hangupedAt":"2017-06-19T06:17:41","startedAt":"2017-06-19T06:16:55","recordFile":"http://185.22.65.50/monitor/2017/06/19/in-+77470941200-+77017818681-20170619-121655-1497853015.9753.wav","status":3,"watingDuration":11000,"asterisk_call_id":1497853015,"crm_call_id":""}