{"answeredAt":"2017-06-06T10:45:58","bridgedAt":"2017-06-06T10:45:49","callDuration":171000,"calleePhoneNumber":"87787460214","callerPhoneNumber":"87018885012","conversationDuration":163000,"createdAt":"2017-06-06T10:45:49","direction":"1","displayCallDuration":"01:06","displayConvDuration":"00:58","displayWatingDuration":"00:08","endpointPhoneNumber":"87010999898","hangupedAt":"2017-06-06T10:46:56","startedAt":"2017-06-06T10:45:49","recordFile":"http://185.22.65.50/monitor/2017/06/06/in-+77787460214-+77018885012-20170606-164549-1496745949.5732.wav","status":3,"watingDuration":8000,"asterisk_call_id":1496745949,"crm_call_id":""}