{"answeredAt":"2017-06-19T09:27:03","bridgedAt":"2017-06-19T09:26:55","callDuration":171000,"calleePhoneNumber":"87470940002","callerPhoneNumber":"87079399514","conversationDuration":163000,"createdAt":"2017-06-19T09:26:55","direction":"1","displayCallDuration":"00:11","displayConvDuration":"00:03","displayWatingDuration":"00:08","endpointPhoneNumber":"87765544888","hangupedAt":"2017-06-19T09:27:06","startedAt":"2017-06-19T09:26:55","recordFile":"http://185.22.65.50/monitor/2017/06/19/in-+77470940002-+77079399514-20170619-152655-1497864415.9960.wav","status":3,"watingDuration":8000,"asterisk_call_id":1497864415,"crm_call_id":""}