{"answeredAt":"2017-06-05T07:16:48","bridgedAt":"2017-06-05T07:16:37","callDuration":171000,"calleePhoneNumber":"87787463348","callerPhoneNumber":"87755339673","conversationDuration":163000,"createdAt":"2017-06-05T07:16:37","direction":"1","displayCallDuration":"01:12","displayConvDuration":"01:01","displayWatingDuration":"00:11","endpointPhoneNumber":"87079452857","hangupedAt":"2017-06-05T07:17:49","startedAt":"2017-06-05T07:16:37","recordFile":"http://185.22.65.50/monitor/2017/06/05/in-+77787463348-+77755339673-20170605-131637-1496646997.5399.wav","status":3,"watingDuration":11000,"asterisk_call_id":1496646997,"crm_call_id":""}